bytemesumai/__init__.py
bytemesumai/chunking/__init__.py
bytemesumai/chunking/models.py
bytemesumai/chunking/processor.py
bytemesumai/evaluation/__init__.py
bytemesumai/evaluation/metrics.py
bytemesumai/llm/__init__.py
bytemesumai/llm/client.py
bytemesumai/models/__init__.py
bytemesumai/models/document.py
bytemesumai/processing/__init__.py
bytemesumai/processing/document.py
bytemesumai/reporting/__init__.py
bytemesumai/reporting/markdown.py
bytemesumai/summarization/__init__.py
bytemesumai/summarization/processor.py
bytemesumai/utils/__init__.py
bytemesumai/utils/cache.py
bytemesumai/utils/metrics.py
bytemesumai-0.1.1.dist-info/LICENSE
bytemesumai-0.1.1.dist-info/METADATA
bytemesumai-0.1.1.dist-info/WHEEL
bytemesumai-0.1.1.dist-info/top_level.txt
bytemesumai-0.1.1.dist-info/RECORD
