Metadata-Version: 2.2
Name: bytemesumai
Version: 0.1.1
Summary: Building Blocks for Robust and Context-Aware Retrieval-Augmented Generation
Author-email: Kris Naleszkiewicz <kris.nale@gmail.com>
License: MIT
Project-URL: Homepage, https://github.com/kris-nale314/bytemesumai
Project-URL: Documentation, https://github.com/kris-nale314/bytemesumai/docs
Project-URL: Issues, https://github.com/kris-nale314/bytemesumai/issues
Project-URL: Changelog, https://github.com/kris-nale314/bytemesumai/blob/main/CHANGELOG.md
Keywords: nlp,summarization,document-processing,chunking,ai,llm,rag
Classifier: Development Status :: 3 - Alpha
Classifier: Intended Audience :: Developers
Classifier: License :: OSI Approved :: MIT License
Classifier: Programming Language :: Python :: 3
Classifier: Programming Language :: Python :: 3.8
Classifier: Programming Language :: Python :: 3.9
Classifier: Programming Language :: Python :: 3.10
Classifier: Topic :: Scientific/Engineering :: Artificial Intelligence
Classifier: Topic :: Text Processing :: Linguistic
Requires-Python: >=3.8
License-File: LICENSE
Requires-Dist: litellm>=1.2.0
Requires-Dist: nltk>=3.6.0
Requires-Dist: numpy>=1.20.0
Provides-Extra: dev
Requires-Dist: pytest>=7.0.0; extra == "dev"
Requires-Dist: black>=23.1.0; extra == "dev"
Requires-Dist: isort>=5.12.0; extra == "dev"
Requires-Dist: mypy>=1.0.0; extra == "dev"
Requires-Dist: ruff>=0.0.54; extra == "dev"
Provides-Extra: docs
Requires-Dist: mkdocs>=1.4.0; extra == "docs"
Requires-Dist: mkdocs-material>=8.5.10; extra == "docs"
Requires-Dist: mkdocstrings[python]>=0.19.0; extra == "docs"
